textual_plot/__init__.py
textual_plot/axis_formatter.py
textual_plot/demo.py
textual_plot/plot_widget.py
textual_plot/py.typed
textual_plot/resources/morning-spectrum.csv
textual_plot-0.10.1.dist-info/METADATA
textual_plot-0.10.1.dist-info/WHEEL
textual_plot-0.10.1.dist-info/entry_points.txt
textual_plot-0.10.1.dist-info/licenses/LICENSE
textual_plot-0.10.1.dist-info/RECORD
