Metadata-Version: 2.4
Name: textual-plot
Version: 0.10.1
Summary: A native plotting widget for Textual apps
Project-URL: Homepage, https://github.com/davidfokkema/textual-plot
Project-URL: Repository, https://github.com/davidfokkema/textual-plot.git
Project-URL: Issues, https://github.com/davidfokkema/textual-plot/issues
Project-URL: Changelog, https://github.com/davidfokkema/textual-plot/blob/main/CHANGELOG.md
Author-email: David Fokkema <davidfokkema@icloud.com>
License-Expression: MIT
License-File: LICENSE
Requires-Python: >=3.10
Requires-Dist: numpy>=2.2.1
Requires-Dist: textual-hires-canvas>=0.14.0
Requires-Dist: textual>=1.0.0
